cheesechaser/__init__.py
cheesechaser/config/__init__.py
cheesechaser/config/meta.py
cheesechaser/datapool/__init__.py
cheesechaser/datapool/anime_pictures.py
cheesechaser/datapool/bangumibase.py
cheesechaser/datapool/base.py
cheesechaser/datapool/civitai.py
cheesechaser/datapool/danbooru.py
cheesechaser/datapool/e621.py
cheesechaser/datapool/fancaps.py
cheesechaser/datapool/gelbooru.py
cheesechaser/datapool/hentaicosplay.py
cheesechaser/datapool/konachan.py
cheesechaser/datapool/nhentai.py
cheesechaser/datapool/nozomi.py
cheesechaser/datapool/realbooru.py
cheesechaser/datapool/rule34.py
cheesechaser/datapool/safebooru.py
cheesechaser/datapool/sankaku.py
cheesechaser/datapool/table.py
cheesechaser/datapool/threedbooru.py
cheesechaser/datapool/yande.py
cheesechaser/datapool/zerochan.py
cheesechaser/pipe/__init__.py
cheesechaser/pipe/base.py
cheesechaser/pipe/image.py
cheesechaser/query/__init__.py
cheesechaser/query/base.py
cheesechaser/query/danbooru.py
cheesechaser/query/gelbooru.py
cheesechaser/query/nozomi.py
cheesechaser/utils/__init__.py
cheesechaser/utils/huggingface.py
cheesechaser/utils/session.py
cheesechaser-0.2.2.dist-info/LICENSE
cheesechaser-0.2.2.dist-info/METADATA
cheesechaser-0.2.2.dist-info/WHEEL
cheesechaser-0.2.2.dist-info/top_level.txt
cheesechaser-0.2.2.dist-info/RECORD
